vibeops/__init__.py
vibeops/__main__.py
vibeops/cli.py
vibeops-0.3.1.dist-info/licenses/LICENSE
vibeops-0.3.1.dist-info/METADATA
vibeops-0.3.1.dist-info/WHEEL
vibeops-0.3.1.dist-info/entry_points.txt
vibeops-0.3.1.dist-info/top_level.txt
vibeops-0.3.1.dist-info/RECORD
