Metadata-Version: 2.4
Name: vibeops
Version: 0.3.1
Summary: Configure Cursor to use VibeOps MCP server for DevOps automation
Home-page: https://github.com/vibeops/vibeops
Author: VibeOps Team
Author-email: VibeOps Team <team@vibeops.tech>
License-Expression: MIT
Project-URL: Homepage, https://github.com/vibeops/vibeops
Project-URL: Documentation, https://docs.vibeops.tech
Project-URL: Repository, https://github.com/vibeops/vibeops
Project-URL: Bug Tracker, https://github.com/vibeops/vibeops/issues
Keywords: devops,automation,deployment,mcp,cursor,configuration,ai-powered
Classifier: Development Status :: 4 - Beta
Classifier: Intended Audience :: Developers
Classifier: Topic :: Software Development :: Build Tools
Classifier: Topic :: System :: Systems Administration
Classifier: Programming Language :: Python :: 3
Classifier: Programming Language :: Python :: 3.8
Classifier: Programming Language :: Python :: 3.9
Classifier: Programming Language :: Python :: 3.10
Classifier: Programming Language :: Python :: 3.11
Classifier: Programming Language :: Python :: 3.12
Classifier: Operating System :: OS Independent
Classifier: Environment :: Console
Requires-Python: >=3.8
License-File: LICENSE
Requires-Dist: click>=8.0.0
Requires-Dist: rich>=13.0.0
Requires-Dist: requests>=2.28.0
Provides-Extra: dev
Requires-Dist: pytest>=7.0.0; extra == "dev"
Requires-Dist: black>=23.0.0; extra == "dev"
Requires-Dist: flake8>=6.0.0; extra == "dev"
Dynamic: author
Dynamic: home-page
Dynamic: license-file
Dynamic: requires-python
